ds_utility/__init__.py
ds_utility/_repo_version.py
ds_utility/data/.gitkeep
ds_utility/data/__init__.py
ds_utility/features/.gitkeep
ds_utility/features/__init__.py
ds_utility/mlflow/sklearn_utils.py
ds_utility/models/.gitkeep
ds_utility/models/__init__.py
ds_utility/visualization/.gitkeep
ds_utility/visualization/__init__.py
ds_utility-0.1.2.dist-info/LICENSE
ds_utility-0.1.2.dist-info/METADATA
ds_utility-0.1.2.dist-info/WHEEL
ds_utility-0.1.2.dist-info/entry_points.txt
ds_utility-0.1.2.dist-info/top_level.txt
ds_utility-0.1.2.dist-info/RECORD
