Metadata-Version: 2.1
Name: ds-utility
Version: 0.1.2
Summary: Utility functions for Data Science related works.
Home-page: https://www.linkedin.com/in/skshahidur/
Author: skshahidur
Author-email: skshahidur@gmail.com
License: UNKNOWN
Download-URL: https://github.com/skshahidur/ds-utility/archive/refs/tags/0.1.0.tar.gz
Keywords: DSUTILS,DSUTILITIES,DATASCIENCEUTILITY,DATASCIENCEUTILITIES
Platform: UNKNOWN
Requires-Python: >=3.9.0
License-File: LICENSE
Requires-Dist: click
Requires-Dist: Sphinx
Requires-Dist: coverage
Requires-Dist: awscli
Requires-Dist: flake8
Requires-Dist: python-dotenv (>=0.5.1)
Requires-Dist: scikit-learn (~=1.0.1)
Requires-Dist: pandas (~=1.3.4)
Requires-Dist: dataframe-image (~=0.1.1)
Requires-Dist: structlog (~=21.4.0)
Requires-Dist: numpy (~=1.21.4)
Requires-Dist: scikit-image (~=0.19.0)
Requires-Dist: matplotlib (~=3.5.0)
Provides-Extra: all
Requires-Dist: scikit-learn ; extra == 'all'
Requires-Dist: mlflow ; extra == 'all'
Requires-Dist: matplotlib ; extra == 'all'
Provides-Extra: mlflow
Requires-Dist: scikit-learn ; extra == 'mlflow'
Requires-Dist: mlflow ; extra == 'mlflow'
Provides-Extra: plot
Requires-Dist: matplotlib ; extra == 'plot'
